exifplus/__init__.py
exifplus/__main__.py
exifplus/app.py
exifplus-1.2.1.dist-info/licenses/LICENSE
exifplus-1.2.1.dist-info/METADATA
exifplus-1.2.1.dist-info/WHEEL
exifplus-1.2.1.dist-info/top_level.txt
exifplus-1.2.1.dist-info/RECORD
