Metadata-Version: 2.4
Name: exifplus
Version: 1.2.1
Summary: A simple EXIF metadata viewer and editor.
Author-email: Mohammed Zahid Wadiwale <info@webaon.com>
License-Expression: BSD-3-Clause
Project-URL: Homepage, https://github.com/ZahidServers/ExifPlus
Project-URL: Source, https://github.com/ZahidServers/ExifPlus
Project-URL: Issues, https://github.com/ZahidServers/ExifPlus/issues
Classifier: Programming Language :: Python :: 3
Classifier: Programming Language :: Python :: 3.9
Classifier: Programming Language :: Python :: 3.10
Classifier: Programming Language :: Python :: 3.11
Classifier: Programming Language :: Python :: 3.12
Classifier: Operating System :: OS Independent
Classifier: Intended Audience :: End Users/Desktop
Classifier: Topic :: Multimedia :: Graphics
Requires-Python: >=3.9
License-File: LICENSE
Requires-Dist: pyexiv2
Requires-Dist: hachoir
Requires-Dist: ttkbootstrap
Requires-Dist: exifread
Dynamic: license-file
